<annotation>
        <folder>FOLDER</folder>
        <filename>010690890.jpg</filename>
        <path>..data/images/010690890.jpg</path>
        <source>
                <database>Unknown</database>
        </source>
        <size>
                <width>608</width>
                <height>608</height>
                <depth>3</depth>
        </size>
 <object>
                <name>h13</name>
                <pose>Unspecified</pose>
                <truncated>0</truncated>
                <difficult>0</difficult>
                <bndbox>
                        <xmin>447</xmin>
                        <ymin>534</ymin>
                        <xmax>479</xmax>
                        <ymax>597</ymax>
                </bndbox>
        </object>
 <object>
                <name>h03</name>
                <pose>Unspecified</pose>
                <truncated>0</truncated>
                <difficult>0</difficult>
                <bndbox>
                        <xmin>261</xmin>
                        <ymin>221</ymin>
                        <xmax>294</xmax>
                        <ymax>282</ymax>
                </bndbox>
        </object>
 <object>
                <name>h03</name>
                <pose>Unspecified</pose>
                <truncated>0</truncated>
                <difficult>0</difficult>
                <bndbox>
                        <xmin>474</xmin>
                        <ymin>381</ymin>
                        <xmax>506</xmax>
                        <ymax>442</ymax>
                </bndbox>
        </object>
</annotation>
