<annotation>
        <folder>FOLDER</folder>
        <filename>084400205.jpg</filename>
        <path>..data/images/084400205.jpg</path>
        <source>
                <database>Unknown</database>
        </source>
        <size>
                <width>608</width>
                <height>608</height>
                <depth>3</depth>
        </size>
 <object>
                <name>d02</name>
                <pose>Unspecified</pose>
                <truncated>0</truncated>
                <difficult>0</difficult>
                <bndbox>
                        <xmin>173</xmin>
                        <ymin>512</ymin>
                        <xmax>219</xmax>
                        <ymax>564</ymax>
                </bndbox>
        </object>
 <object>
                <name>s07</name>
                <pose>Unspecified</pose>
                <truncated>0</truncated>
                <difficult>0</difficult>
                <bndbox>
                        <xmin>165</xmin>
                        <ymin>28</ymin>
                        <xmax>250</xmax>
                        <ymax>98</ymax>
                </bndbox>
        </object>
 <object>
                <name>s07</name>
                <pose>Unspecified</pose>
                <truncated>0</truncated>
                <difficult>0</difficult>
                <bndbox>
                        <xmin>61</xmin>
                        <ymin>423</ymin>
                        <xmax>147</xmax>
                        <ymax>495</ymax>
                </bndbox>
        </object>
</annotation>
