<annotation>
        <folder>FOLDER</folder>
        <filename>118169254.jpg</filename>
        <path>..data/images/118169254.jpg</path>
        <source>
                <database>Unknown</database>
        </source>
        <size>
                <width>608</width>
                <height>608</height>
                <depth>3</depth>
        </size>
 <object>
                <name>h08</name>
                <pose>Unspecified</pose>
                <truncated>0</truncated>
                <difficult>0</difficult>
                <bndbox>
                        <xmin>286</xmin>
                        <ymin>76</ymin>
                        <xmax>314</xmax>
                        <ymax>138</ymax>
                </bndbox>
        </object>
 <object>
                <name>c09</name>
                <pose>Unspecified</pose>
                <truncated>0</truncated>
                <difficult>0</difficult>
                <bndbox>
                        <xmin>354</xmin>
                        <ymin>486</ymin>
                        <xmax>435</xmax>
                        <ymax>557</ymax>
                </bndbox>
        </object>
 <object>
                <name>c09</name>
                <pose>Unspecified</pose>
                <truncated>0</truncated>
                <difficult>0</difficult>
                <bndbox>
                        <xmin>456</xmin>
                        <ymin>97</ymin>
                        <xmax>538</xmax>
                        <ymax>169</ymax>
                </bndbox>
        </object>
</annotation>
