<annotation>
        <folder>FOLDER</folder>
        <filename>125310705.jpg</filename>
        <path>..data/images/125310705.jpg</path>
        <source>
                <database>Unknown</database>
        </source>
        <size>
                <width>608</width>
                <height>608</height>
                <depth>3</depth>
        </size>
 <object>
                <name>d05</name>
                <pose>Unspecified</pose>
                <truncated>0</truncated>
                <difficult>0</difficult>
                <bndbox>
                        <xmin>382</xmin>
                        <ymin>473</ymin>
                        <xmax>418</xmax>
                        <ymax>533</ymax>
                </bndbox>
        </object>
 <object>
                <name>c05</name>
                <pose>Unspecified</pose>
                <truncated>0</truncated>
                <difficult>0</difficult>
                <bndbox>
                        <xmin>287</xmin>
                        <ymin>110</ymin>
                        <xmax>338</xmax>
                        <ymax>166</ymax>
                </bndbox>
        </object>
 <object>
                <name>c05</name>
                <pose>Unspecified</pose>
                <truncated>0</truncated>
                <difficult>0</difficult>
                <bndbox>
                        <xmin>292</xmin>
                        <ymin>375</ymin>
                        <xmax>343</xmax>
                        <ymax>431</ymax>
                </bndbox>
        </object>
</annotation>
