<annotation>
        <folder>FOLDER</folder>
        <filename>134825653.jpg</filename>
        <path>..data/images/134825653.jpg</path>
        <source>
                <database>Unknown</database>
        </source>
        <size>
                <width>608</width>
                <height>608</height>
                <depth>3</depth>
        </size>
 <object>
                <name>c10</name>
                <pose>Unspecified</pose>
                <truncated>0</truncated>
                <difficult>0</difficult>
                <bndbox>
                        <xmin>202</xmin>
                        <ymin>286</ymin>
                        <xmax>261</xmax>
                        <ymax>330</ymax>
                </bndbox>
        </object>
 <object>
                <name>c10</name>
                <pose>Unspecified</pose>
                <truncated>0</truncated>
                <difficult>0</difficult>
                <bndbox>
                        <xmin>319</xmin>
                        <ymin>50</ymin>
                        <xmax>379</xmax>
                        <ymax>93</ymax>
                </bndbox>
        </object>
 <object>
                <name>c09</name>
                <pose>Unspecified</pose>
                <truncated>0</truncated>
                <difficult>0</difficult>
                <bndbox>
                        <xmin>329</xmin>
                        <ymin>230</ymin>
                        <xmax>364</xmax>
                        <ymax>291</ymax>
                </bndbox>
        </object>
 <object>
                <name>c09</name>
                <pose>Unspecified</pose>
                <truncated>0</truncated>
                <difficult>0</difficult>
                <bndbox>
                        <xmin>537</xmin>
                        <ymin>387</ymin>
                        <xmax>572</xmax>
                        <ymax>448</ymax>
                </bndbox>
        </object>
</annotation>
