<annotation>
        <folder>FOLDER</folder>
        <filename>145516082.jpg</filename>
        <path>..data/images/145516082.jpg</path>
        <source>
                <database>Unknown</database>
        </source>
        <size>
                <width>608</width>
                <height>608</height>
                <depth>3</depth>
        </size>
 <object>
                <name>h09</name>
                <pose>Unspecified</pose>
                <truncated>0</truncated>
                <difficult>0</difficult>
                <bndbox>
                        <xmin>435</xmin>
                        <ymin>329</ymin>
                        <xmax>471</xmax>
                        <ymax>390</ymax>
                </bndbox>
        </object>
 <object>
                <name>c03</name>
                <pose>Unspecified</pose>
                <truncated>0</truncated>
                <difficult>0</difficult>
                <bndbox>
                        <xmin>464</xmin>
                        <ymin>155</ymin>
                        <xmax>542</xmax>
                        <ymax>238</ymax>
                </bndbox>
        </object>
 <object>
                <name>c03</name>
                <pose>Unspecified</pose>
                <truncated>0</truncated>
                <difficult>0</difficult>
                <bndbox>
                        <xmin>63</xmin>
                        <ymin>81</ymin>
                        <xmax>141</xmax>
                        <ymax>165</ymax>
                </bndbox>
        </object>
</annotation>
