<annotation>
        <folder>FOLDER</folder>
        <filename>170974236.jpg</filename>
        <path>..data/images/170974236.jpg</path>
        <source>
                <database>Unknown</database>
        </source>
        <size>
                <width>608</width>
                <height>608</height>
                <depth>3</depth>
        </size>
 <object>
                <name>h12</name>
                <pose>Unspecified</pose>
                <truncated>0</truncated>
                <difficult>0</difficult>
                <bndbox>
                        <xmin>346</xmin>
                        <ymin>518</ymin>
                        <xmax>380</xmax>
                        <ymax>577</ymax>
                </bndbox>
        </object>
 <object>
                <name>s13</name>
                <pose>Unspecified</pose>
                <truncated>0</truncated>
                <difficult>0</difficult>
                <bndbox>
                        <xmin>187</xmin>
                        <ymin>290</ymin>
                        <xmax>247</xmax>
                        <ymax>339</ymax>
                </bndbox>
        </object>
 <object>
                <name>s13</name>
                <pose>Unspecified</pose>
                <truncated>0</truncated>
                <difficult>0</difficult>
                <bndbox>
                        <xmin>449</xmin>
                        <ymin>261</ymin>
                        <xmax>509</xmax>
                        <ymax>311</ymax>
                </bndbox>
        </object>
</annotation>
