<annotation>
        <folder>FOLDER</folder>
        <filename>179332608.jpg</filename>
        <path>..data/images/179332608.jpg</path>
        <source>
                <database>Unknown</database>
        </source>
        <size>
                <width>608</width>
                <height>608</height>
                <depth>3</depth>
        </size>
 <object>
                <name>h04</name>
                <pose>Unspecified</pose>
                <truncated>0</truncated>
                <difficult>0</difficult>
                <bndbox>
                        <xmin>363</xmin>
                        <ymin>214</ymin>
                        <xmax>424</xmax>
                        <ymax>246</ymax>
                </bndbox>
        </object>
 <object>
                <name>s10</name>
                <pose>Unspecified</pose>
                <truncated>0</truncated>
                <difficult>0</difficult>
                <bndbox>
                        <xmin>75</xmin>
                        <ymin>442</ymin>
                        <xmax>171</xmax>
                        <ymax>494</ymax>
                </bndbox>
        </object>
 <object>
                <name>s10</name>
                <pose>Unspecified</pose>
                <truncated>0</truncated>
                <difficult>0</difficult>
                <bndbox>
                        <xmin>442</xmin>
                        <ymin>279</ymin>
                        <xmax>538</xmax>
                        <ymax>330</ymax>
                </bndbox>
        </object>
</annotation>
