<annotation>
        <folder>FOLDER</folder>
        <filename>193275948.jpg</filename>
        <path>..data/images/193275948.jpg</path>
        <source>
                <database>Unknown</database>
        </source>
        <size>
                <width>608</width>
                <height>608</height>
                <depth>3</depth>
        </size>
 <object>
                <name>c04</name>
                <pose>Unspecified</pose>
                <truncated>0</truncated>
                <difficult>0</difficult>
                <bndbox>
                        <xmin>27</xmin>
                        <ymin>466</ymin>
                        <xmax>82</xmax>
                        <ymax>503</ymax>
                </bndbox>
        </object>
 <object>
                <name>s02</name>
                <pose>Unspecified</pose>
                <truncated>0</truncated>
                <difficult>0</difficult>
                <bndbox>
                        <xmin>209</xmin>
                        <ymin>431</ymin>
                        <xmax>272</xmax>
                        <ymax>462</ymax>
                </bndbox>
        </object>
 <object>
                <name>s02</name>
                <pose>Unspecified</pose>
                <truncated>0</truncated>
                <difficult>0</difficult>
                <bndbox>
                        <xmin>437</xmin>
                        <ymin>306</ymin>
                        <xmax>500</xmax>
                        <ymax>338</ymax>
                </bndbox>
        </object>
</annotation>
