<annotation>
        <folder>FOLDER</folder>
        <filename>241316500.jpg</filename>
        <path>..data/images/241316500.jpg</path>
        <source>
                <database>Unknown</database>
        </source>
        <size>
                <width>608</width>
                <height>608</height>
                <depth>3</depth>
        </size>
 <object>
                <name>c03</name>
                <pose>Unspecified</pose>
                <truncated>0</truncated>
                <difficult>0</difficult>
                <bndbox>
                        <xmin>216</xmin>
                        <ymin>472</ymin>
                        <xmax>278</xmax>
                        <ymax>501</ymax>
                </bndbox>
        </object>
 <object>
                <name>c03</name>
                <pose>Unspecified</pose>
                <truncated>0</truncated>
                <difficult>0</difficult>
                <bndbox>
                        <xmin>424</xmin>
                        <ymin>310</ymin>
                        <xmax>486</xmax>
                        <ymax>339</ymax>
                </bndbox>
        </object>
 <object>
                <name>d06</name>
                <pose>Unspecified</pose>
                <truncated>0</truncated>
                <difficult>0</difficult>
                <bndbox>
                        <xmin>411</xmin>
                        <ymin>204</ymin>
                        <xmax>448</xmax>
                        <ymax>263</ymax>
                </bndbox>
        </object>
 <object>
                <name>d06</name>
                <pose>Unspecified</pose>
                <truncated>0</truncated>
                <difficult>0</difficult>
                <bndbox>
                        <xmin>176</xmin>
                        <ymin>81</ymin>
                        <xmax>213</xmax>
                        <ymax>140</ymax>
                </bndbox>
        </object>
</annotation>
