<annotation>
        <folder>FOLDER</folder>
        <filename>275774310.jpg</filename>
        <path>..data/images/275774310.jpg</path>
        <source>
                <database>Unknown</database>
        </source>
        <size>
                <width>608</width>
                <height>608</height>
                <depth>3</depth>
        </size>
 <object>
                <name>c07</name>
                <pose>Unspecified</pose>
                <truncated>0</truncated>
                <difficult>0</difficult>
                <bndbox>
                        <xmin>276</xmin>
                        <ymin>490</ymin>
                        <xmax>306</xmax>
                        <ymax>552</ymax>
                </bndbox>
        </object>
 <object>
                <name>c08</name>
                <pose>Unspecified</pose>
                <truncated>0</truncated>
                <difficult>0</difficult>
                <bndbox>
                        <xmin>73</xmin>
                        <ymin>415</ymin>
                        <xmax>164</xmax>
                        <ymax>458</ymax>
                </bndbox>
        </object>
 <object>
                <name>c08</name>
                <pose>Unspecified</pose>
                <truncated>0</truncated>
                <difficult>0</difficult>
                <bndbox>
                        <xmin>409</xmin>
                        <ymin>185</ymin>
                        <xmax>500</xmax>
                        <ymax>229</ymax>
                </bndbox>
        </object>
</annotation>
