<annotation>
        <folder>FOLDER</folder>
        <filename>322664232.jpg</filename>
        <path>..data/images/322664232.jpg</path>
        <source>
                <database>Unknown</database>
        </source>
        <size>
                <width>608</width>
                <height>608</height>
                <depth>3</depth>
        </size>
 <object>
                <name>s07</name>
                <pose>Unspecified</pose>
                <truncated>0</truncated>
                <difficult>0</difficult>
                <bndbox>
                        <xmin>420</xmin>
                        <ymin>474</ymin>
                        <xmax>468</xmax>
                        <ymax>568</ymax>
                </bndbox>
        </object>
 <object>
                <name>s09</name>
                <pose>Unspecified</pose>
                <truncated>0</truncated>
                <difficult>0</difficult>
                <bndbox>
                        <xmin>255</xmin>
                        <ymin>20</ymin>
                        <xmax>343</xmax>
                        <ymax>80</ymax>
                </bndbox>
        </object>
 <object>
                <name>s09</name>
                <pose>Unspecified</pose>
                <truncated>0</truncated>
                <difficult>0</difficult>
                <bndbox>
                        <xmin>94</xmin>
                        <ymin>390</ymin>
                        <xmax>184</xmax>
                        <ymax>450</ymax>
                </bndbox>
        </object>
</annotation>
