<annotation>
        <folder>FOLDER</folder>
        <filename>439410315.jpg</filename>
        <path>..data/images/439410315.jpg</path>
        <source>
                <database>Unknown</database>
        </source>
        <size>
                <width>608</width>
                <height>608</height>
                <depth>3</depth>
        </size>
 <object>
                <name>c08</name>
                <pose>Unspecified</pose>
                <truncated>0</truncated>
                <difficult>0</difficult>
                <bndbox>
                        <xmin>485</xmin>
                        <ymin>370</ymin>
                        <xmax>572</xmax>
                        <ymax>434</ymax>
                </bndbox>
        </object>
 <object>
                <name>c08</name>
                <pose>Unspecified</pose>
                <truncated>0</truncated>
                <difficult>0</difficult>
                <bndbox>
                        <xmin>92</xmin>
                        <ymin>471</ymin>
                        <xmax>178</xmax>
                        <ymax>534</ymax>
                </bndbox>
        </object>
 <object>
                <name>d09</name>
                <pose>Unspecified</pose>
                <truncated>0</truncated>
                <difficult>0</difficult>
                <bndbox>
                        <xmin>166</xmin>
                        <ymin>331</ymin>
                        <xmax>221</xmax>
                        <ymax>372</ymax>
                </bndbox>
        </object>
 <object>
                <name>d09</name>
                <pose>Unspecified</pose>
                <truncated>0</truncated>
                <difficult>0</difficult>
                <bndbox>
                        <xmin>428</xmin>
                        <ymin>291</ymin>
                        <xmax>483</xmax>
                        <ymax>332</ymax>
                </bndbox>
        </object>
</annotation>
