<annotation>
        <folder>FOLDER</folder>
        <filename>457177446.jpg</filename>
        <path>..data/images/457177446.jpg</path>
        <source>
                <database>Unknown</database>
        </source>
        <size>
                <width>608</width>
                <height>608</height>
                <depth>3</depth>
        </size>
 <object>
                <name>c08</name>
                <pose>Unspecified</pose>
                <truncated>0</truncated>
                <difficult>0</difficult>
                <bndbox>
                        <xmin>94</xmin>
                        <ymin>83</ymin>
                        <xmax>133</xmax>
                        <ymax>143</ymax>
                </bndbox>
        </object>
 <object>
                <name>h01</name>
                <pose>Unspecified</pose>
                <truncated>0</truncated>
                <difficult>0</difficult>
                <bndbox>
                        <xmin>433</xmin>
                        <ymin>188</ymin>
                        <xmax>491</xmax>
                        <ymax>222</ymax>
                </bndbox>
        </object>
 <object>
                <name>h01</name>
                <pose>Unspecified</pose>
                <truncated>0</truncated>
                <difficult>0</difficult>
                <bndbox>
                        <xmin>179</xmin>
                        <ymin>251</ymin>
                        <xmax>236</xmax>
                        <ymax>285</ymax>
                </bndbox>
        </object>
</annotation>
