<annotation>
        <folder>FOLDER</folder>
        <filename>521181803.jpg</filename>
        <path>..data/images/521181803.jpg</path>
        <source>
                <database>Unknown</database>
        </source>
        <size>
                <width>608</width>
                <height>608</height>
                <depth>3</depth>
        </size>
 <object>
                <name>h02</name>
                <pose>Unspecified</pose>
                <truncated>0</truncated>
                <difficult>0</difficult>
                <bndbox>
                        <xmin>469</xmin>
                        <ymin>480</ymin>
                        <xmax>503</xmax>
                        <ymax>541</ymax>
                </bndbox>
        </object>
 <object>
                <name>d02</name>
                <pose>Unspecified</pose>
                <truncated>0</truncated>
                <difficult>0</difficult>
                <bndbox>
                        <xmin>317</xmin>
                        <ymin>295</ymin>
                        <xmax>365</xmax>
                        <ymax>344</ymax>
                </bndbox>
        </object>
 <object>
                <name>d02</name>
                <pose>Unspecified</pose>
                <truncated>0</truncated>
                <difficult>0</difficult>
                <bndbox>
                        <xmin>336</xmin>
                        <ymin>29</ymin>
                        <xmax>384</xmax>
                        <ymax>78</ymax>
                </bndbox>
        </object>
</annotation>
