<annotation>
        <folder>FOLDER</folder>
        <filename>537512057.jpg</filename>
        <path>..data/images/537512057.jpg</path>
        <source>
                <database>Unknown</database>
        </source>
        <size>
                <width>608</width>
                <height>608</height>
                <depth>3</depth>
        </size>
 <object>
                <name>s03</name>
                <pose>Unspecified</pose>
                <truncated>0</truncated>
                <difficult>0</difficult>
                <bndbox>
                        <xmin>414</xmin>
                        <ymin>510</ymin>
                        <xmax>441</xmax>
                        <ymax>574</ymax>
                </bndbox>
        </object>
 <object>
                <name>d02</name>
                <pose>Unspecified</pose>
                <truncated>0</truncated>
                <difficult>0</difficult>
                <bndbox>
                        <xmin>124</xmin>
                        <ymin>302</ymin>
                        <xmax>158</xmax>
                        <ymax>361</ymax>
                </bndbox>
        </object>
 <object>
                <name>d02</name>
                <pose>Unspecified</pose>
                <truncated>0</truncated>
                <difficult>0</difficult>
                <bndbox>
                        <xmin>348</xmin>
                        <ymin>444</ymin>
                        <xmax>383</xmax>
                        <ymax>503</ymax>
                </bndbox>
        </object>
</annotation>
