<annotation>
        <folder>FOLDER</folder>
        <filename>538078187.jpg</filename>
        <path>..data/images/538078187.jpg</path>
        <source>
                <database>Unknown</database>
        </source>
        <size>
                <width>608</width>
                <height>608</height>
                <depth>3</depth>
        </size>
 <object>
                <name>c12</name>
                <pose>Unspecified</pose>
                <truncated>0</truncated>
                <difficult>0</difficult>
                <bndbox>
                        <xmin>130</xmin>
                        <ymin>287</ymin>
                        <xmax>159</xmax>
                        <ymax>348</ymax>
                </bndbox>
        </object>
 <object>
                <name>c12</name>
                <pose>Unspecified</pose>
                <truncated>0</truncated>
                <difficult>0</difficult>
                <bndbox>
                        <xmin>294</xmin>
                        <ymin>494</ymin>
                        <xmax>323</xmax>
                        <ymax>555</ymax>
                </bndbox>
        </object>
 <object>
                <name>c04</name>
                <pose>Unspecified</pose>
                <truncated>0</truncated>
                <difficult>0</difficult>
                <bndbox>
                        <xmin>262</xmin>
                        <ymin>224</ymin>
                        <xmax>302</xmax>
                        <ymax>282</ymax>
                </bndbox>
        </object>
 <object>
                <name>c04</name>
                <pose>Unspecified</pose>
                <truncated>0</truncated>
                <difficult>0</difficult>
                <bndbox>
                        <xmin>504</xmin>
                        <ymin>300</ymin>
                        <xmax>543</xmax>
                        <ymax>356</ymax>
                </bndbox>
        </object>
</annotation>
