<annotation>
        <folder>FOLDER</folder>
        <filename>559405372.jpg</filename>
        <path>..data/images/559405372.jpg</path>
        <source>
                <database>Unknown</database>
        </source>
        <size>
                <width>608</width>
                <height>608</height>
                <depth>3</depth>
        </size>
 <object>
                <name>h08</name>
                <pose>Unspecified</pose>
                <truncated>0</truncated>
                <difficult>0</difficult>
                <bndbox>
                        <xmin>53</xmin>
                        <ymin>63</ymin>
                        <xmax>101</xmax>
                        <ymax>151</ymax>
                </bndbox>
        </object>
 <object>
                <name>h08</name>
                <pose>Unspecified</pose>
                <truncated>0</truncated>
                <difficult>0</difficult>
                <bndbox>
                        <xmin>216</xmin>
                        <ymin>433</ymin>
                        <xmax>265</xmax>
                        <ymax>521</ymax>
                </bndbox>
        </object>
 <object>
                <name>d05</name>
                <pose>Unspecified</pose>
                <truncated>0</truncated>
                <difficult>0</difficult>
                <bndbox>
                        <xmin>540</xmin>
                        <ymin>329</ymin>
                        <xmax>600</xmax>
                        <ymax>365</ymax>
                </bndbox>
        </object>
 <object>
                <name>d05</name>
                <pose>Unspecified</pose>
                <truncated>0</truncated>
                <difficult>0</difficult>
                <bndbox>
                        <xmin>292</xmin>
                        <ymin>418</ymin>
                        <xmax>352</xmax>
                        <ymax>453</ymax>
                </bndbox>
        </object>
</annotation>
