<annotation>
        <folder>FOLDER</folder>
        <filename>606537359.jpg</filename>
        <path>..data/images/606537359.jpg</path>
        <source>
                <database>Unknown</database>
        </source>
        <size>
                <width>608</width>
                <height>608</height>
                <depth>3</depth>
        </size>
 <object>
                <name>s03</name>
                <pose>Unspecified</pose>
                <truncated>0</truncated>
                <difficult>0</difficult>
                <bndbox>
                        <xmin>364</xmin>
                        <ymin>491</ymin>
                        <xmax>413</xmax>
                        <ymax>586</ymax>
                </bndbox>
        </object>
 <object>
                <name>s03</name>
                <pose>Unspecified</pose>
                <truncated>0</truncated>
                <difficult>0</difficult>
                <bndbox>
                        <xmin>40</xmin>
                        <ymin>249</ymin>
                        <xmax>89</xmax>
                        <ymax>345</ymax>
                </bndbox>
        </object>
 <object>
                <name>c06</name>
                <pose>Unspecified</pose>
                <truncated>0</truncated>
                <difficult>0</difficult>
                <bndbox>
                        <xmin>111</xmin>
                        <ymin>243</ymin>
                        <xmax>172</xmax>
                        <ymax>273</ymax>
                </bndbox>
        </object>
 <object>
                <name>c06</name>
                <pose>Unspecified</pose>
                <truncated>0</truncated>
                <difficult>0</difficult>
                <bndbox>
                        <xmin>290</xmin>
                        <ymin>53</ymin>
                        <xmax>351</xmax>
                        <ymax>84</ymax>
                </bndbox>
        </object>
</annotation>
