<annotation>
        <folder>FOLDER</folder>
        <filename>669874341.jpg</filename>
        <path>..data/images/669874341.jpg</path>
        <source>
                <database>Unknown</database>
        </source>
        <size>
                <width>608</width>
                <height>608</height>
                <depth>3</depth>
        </size>
 <object>
                <name>s03</name>
                <pose>Unspecified</pose>
                <truncated>0</truncated>
                <difficult>0</difficult>
                <bndbox>
                        <xmin>514</xmin>
                        <ymin>307</ymin>
                        <xmax>565</xmax>
                        <ymax>365</ymax>
                </bndbox>
        </object>
 <object>
                <name>s05</name>
                <pose>Unspecified</pose>
                <truncated>0</truncated>
                <difficult>0</difficult>
                <bndbox>
                        <xmin>313</xmin>
                        <ymin>229</ymin>
                        <xmax>374</xmax>
                        <ymax>273</ymax>
                </bndbox>
        </object>
 <object>
                <name>s05</name>
                <pose>Unspecified</pose>
                <truncated>0</truncated>
                <difficult>0</difficult>
                <bndbox>
                        <xmin>55</xmin>
                        <ymin>277</ymin>
                        <xmax>115</xmax>
                        <ymax>321</ymax>
                </bndbox>
        </object>
</annotation>
