<annotation>
        <folder>FOLDER</folder>
        <filename>752538476.jpg</filename>
        <path>..data/images/752538476.jpg</path>
        <source>
                <database>Unknown</database>
        </source>
        <size>
                <width>608</width>
                <height>608</height>
                <depth>3</depth>
        </size>
 <object>
                <name>c03</name>
                <pose>Unspecified</pose>
                <truncated>0</truncated>
                <difficult>0</difficult>
                <bndbox>
                        <xmin>430</xmin>
                        <ymin>420</ymin>
                        <xmax>476</xmax>
                        <ymax>479</ymax>
                </bndbox>
        </object>
 <object>
                <name>c13</name>
                <pose>Unspecified</pose>
                <truncated>0</truncated>
                <difficult>0</difficult>
                <bndbox>
                        <xmin>393</xmin>
                        <ymin>125</ymin>
                        <xmax>485</xmax>
                        <ymax>178</ymax>
                </bndbox>
        </object>
 <object>
                <name>c13</name>
                <pose>Unspecified</pose>
                <truncated>0</truncated>
                <difficult>0</difficult>
                <bndbox>
                        <xmin>39</xmin>
                        <ymin>325</ymin>
                        <xmax>132</xmax>
                        <ymax>376</ymax>
                </bndbox>
        </object>
</annotation>
