<annotation>
        <folder>FOLDER</folder>
        <filename>807956596.jpg</filename>
        <path>..data/images/807956596.jpg</path>
        <source>
                <database>Unknown</database>
        </source>
        <size>
                <width>608</width>
                <height>608</height>
                <depth>3</depth>
        </size>
 <object>
                <name>c05</name>
                <pose>Unspecified</pose>
                <truncated>0</truncated>
                <difficult>0</difficult>
                <bndbox>
                        <xmin>274</xmin>
                        <ymin>500</ymin>
                        <xmax>335</xmax>
                        <ymax>542</ymax>
                </bndbox>
        </object>
 <object>
                <name>d05</name>
                <pose>Unspecified</pose>
                <truncated>0</truncated>
                <difficult>0</difficult>
                <bndbox>
                        <xmin>336</xmin>
                        <ymin>130</ymin>
                        <xmax>397</xmax>
                        <ymax>164</ymax>
                </bndbox>
        </object>
 <object>
                <name>d05</name>
                <pose>Unspecified</pose>
                <truncated>0</truncated>
                <difficult>0</difficult>
                <bndbox>
                        <xmin>195</xmin>
                        <ymin>354</ymin>
                        <xmax>256</xmax>
                        <ymax>389</ymax>
                </bndbox>
        </object>
</annotation>
