<annotation>
        <folder>FOLDER</folder>
        <filename>854115261.jpg</filename>
        <path>..data/images/854115261.jpg</path>
        <source>
                <database>Unknown</database>
        </source>
        <size>
                <width>608</width>
                <height>608</height>
                <depth>3</depth>
        </size>
 <object>
                <name>c04</name>
                <pose>Unspecified</pose>
                <truncated>0</truncated>
                <difficult>0</difficult>
                <bndbox>
                        <xmin>101</xmin>
                        <ymin>460</ymin>
                        <xmax>163</xmax>
                        <ymax>488</ymax>
                </bndbox>
        </object>
 <object>
                <name>d05</name>
                <pose>Unspecified</pose>
                <truncated>0</truncated>
                <difficult>0</difficult>
                <bndbox>
                        <xmin>97</xmin>
                        <ymin>141</ymin>
                        <xmax>171</xmax>
                        <ymax>215</ymax>
                </bndbox>
        </object>
 <object>
                <name>d05</name>
                <pose>Unspecified</pose>
                <truncated>0</truncated>
                <difficult>0</difficult>
                <bndbox>
                        <xmin>505</xmin>
                        <ymin>182</ymin>
                        <xmax>580</xmax>
                        <ymax>257</ymax>
                </bndbox>
        </object>
</annotation>
