<annotation>
        <folder>FOLDER</folder>
        <filename>856217739.jpg</filename>
        <path>..data/images/856217739.jpg</path>
        <source>
                <database>Unknown</database>
        </source>
        <size>
                <width>608</width>
                <height>608</height>
                <depth>3</depth>
        </size>
 <object>
                <name>h08</name>
                <pose>Unspecified</pose>
                <truncated>0</truncated>
                <difficult>0</difficult>
                <bndbox>
                        <xmin>529</xmin>
                        <ymin>402</ymin>
                        <xmax>581</xmax>
                        <ymax>489</ymax>
                </bndbox>
        </object>
 <object>
                <name>h13</name>
                <pose>Unspecified</pose>
                <truncated>0</truncated>
                <difficult>0</difficult>
                <bndbox>
                        <xmin>44</xmin>
                        <ymin>225</ymin>
                        <xmax>88</xmax>
                        <ymax>318</ymax>
                </bndbox>
        </object>
 <object>
                <name>h13</name>
                <pose>Unspecified</pose>
                <truncated>0</truncated>
                <difficult>0</difficult>
                <bndbox>
                        <xmin>361</xmin>
                        <ymin>480</ymin>
                        <xmax>406</xmax>
                        <ymax>574</ymax>
                </bndbox>
        </object>
</annotation>
